job_market_analyzer/__init__.py
job_market_analyzer/analyzer.py
job_market_analyzer/utils.py
job_market_analyzer/visuals.py
job_market_analyzer/data/jobs.csv
job_market_analyzer-0.1.4.dist-info/licenses/LICENSE
job_market_analyzer-0.1.4.dist-info/METADATA
job_market_analyzer-0.1.4.dist-info/WHEEL
job_market_analyzer-0.1.4.dist-info/top_level.txt
job_market_analyzer-0.1.4.dist-info/RECORD
